{
    "res": {
        "XJ.AHQ.00.BHE": {
            "curve_info": {
                "_format": "MSEED",
                "calib": "1",
                "channel": "BHE",
                "curve_id": "XJ.AHQ.00.BHE",
                "delta": "0.01",
                "end_time": "2022-10-16 08:58:16",
                "end_ts": 1665881896,
                "event_type": null,
                "file_name": "XJ.AHQ.00.20221016085459.mseed",
                "id": 37,
                "intensity": null,
                "join_time": "2022-12-25 12:16:09",
                "join_ts": 1671941769,
                "latitude": null,
                "location": "00",
                "longitude": null,
                "magnitude": null,
                "network": "XJ",
                "npts": "25216",
                "p_start_time": null,
                "sampling_rate": "100",
                "start_time": "2022-10-16 08:54:04",
                "start_ts": 1665881644,
                "station": "AHQ"
            },
            "points_info": {
                "raw_datas": [
                    -23,
                    -1,
                    77,
                    34,
                    15,
                    8,
                    -4,
                    16,
                    -58,
                    31,
                    -17,
                    29683,
                    50013,
                    41166,
                    64665,
                    75260,
                    589272,
                    220908,
                    190313,
                    113135,
                    62516,
                    50176,
                    54565,
                    26256,
                    29276,
                    25280,
                    24516,
                    17134,
                    18060,
                    19534,
                    18319,
                    13632,
                    10573,
                    9352,
                    9432,
                    7535,
                    10689,
                    9182,
                    7156,
                    5890,
                    4952,
                    5127,
                    4574,
                    4133,
                    6337,
                    6693,
                    4906,
                    5083,
                    2387,
                    7556,
                    7235,
                    5559
                ],
                "ts": [
                    1671670445,
                    1671670450,
                    1671670455,
                    1671670460,
                    1671670465,
                    1671670470,
                    1671670475,
                    1671670480,
                    1671670485,
                    1671670490,
                    1671670495,
                    1671670500,
                    1671670505,
                    1671670510,
                    1671670515,
                    1671670520,
                    1671670525,
                    1671670530,
                    1671670535,
                    1671670540,
                    1671670545,
                    1671670550,
                    1671670555,
                    1671670560,
                    1671670565,
                    1671670570,
                    1671670575,
                    1671670580,
                    1671670585,
                    1671670590,
                    1671670595,
                    1671670600,
                    1671670605,
                    1671670610,
                    1671670615,
                    1671670620,
                    1671670625,
                    1671670630,
                    1671670635,
                    1671670640,
                    1671670645,
                    1671670650,
                    1671670655,
                    1671670660,
                    1671670665,
                    1671670670,
                    1671670675,
                    1671670680,
                    1671670685,
                    1671670690,
                    1671670695,
                    1671670700
                ]
            }
        },
        "XJ.AHQ.00.BHN": {
            "curve_info": {
                "_format": "MSEED",
                "calib": "1",
                "channel": "BHN",
                "curve_id": "XJ.AHQ.00.BHN",
                "delta": "0.01",
                "end_time": "2022-10-16 08:58:17",
                "end_ts": 1665881897,
                "event_type": null,
                "file_name": "XJ.AHQ.00.20221016085459.mseed",
                "id": 38,
                "intensity": null,
                "join_time": "2022-12-25 12:16:09",
                "join_ts": 1671941769,
                "latitude": null,
                "location": "00",
                "longitude": null,
                "magnitude": null,
                "network": "XJ",
                "npts": "25257",
                "p_start_time": null,
                "sampling_rate": "100",
                "start_time": "2022-10-16 08:54:04",
                "start_ts": 1665881644,
                "station": "AHQ"
            },
            "points_info": {
                "raw_datas": [
                    -105,
                    -73,
                    -68,
                    -103,
                    -21,
                    -22,
                    -19,
                    93,
                    23,
                    81,
                    5,
                    37212,
                    108865,
                    55440,
                    59069,
                    103281,
                    457550,
                    255178,
                    120809,
                    76346,
                    58548,
                    50190,
                    38554,
                    33844,
                    20778,
                    19736,
                    18269,
                    15775,
                    19648,
                    14320,
                    13756,
                    10337,
                    8559,
                    5915,
                    8132,
                    5493,
                    4828,
                    5981,
                    8380,
                    4051,
                    5366,
                    5793,
                    5842,
                    5579,
                    4838,
                    3867,
                    3797,
                    3560,
                    6501,
                    3952,
                    3713,
                    1322
                ],
                "ts": [
                    1671670445,
                    1671670450,
                    1671670455,
                    1671670460,
                    1671670465,
                    1671670470,
                    1671670475,
                    1671670480,
                    1671670485,
                    1671670490,
                    1671670495,
                    1671670500,
                    1671670505,
                    1671670510,
                    1671670515,
                    1671670520,
                    1671670525,
                    1671670530,
                    1671670535,
                    1671670540,
                    1671670545,
                    1671670550,
                    1671670555,
                    1671670560,
                    1671670565,
                    1671670570,
                    1671670575,
                    1671670580,
                    1671670585,
                    1671670590,
                    1671670595,
                    1671670600,
                    1671670605,
                    1671670610,
                    1671670615,
                    1671670620,
                    1671670625,
                    1671670630,
                    1671670635,
                    1671670640,
                    1671670645,
                    1671670650,
                    1671670655,
                    1671670660,
                    1671670665,
                    1671670670,
                    1671670675,
                    1671670680,
                    1671670685,
                    1671670690,
                    1671670695,
                    1671670700
                ]
            }
        }
    },
    "status": 200
}